{
	"name": "Mortar",
	"icon": "immersiveweapons:mortar",
	"category": "immersiveweapons:defense",
	"pages": [
		{
			"type": "patchouli:text",
			"text": "Enemy base too strong to break through via conventional methods? Try an artillery strike.$(br2)Setup a mortar a distance away from the fortifications, and interact ($(k:use)) with an empty hand to set the trajectory. Load a mortar shell into the mortar, and ignite it with flint and steel or a redstone pulse."
		},
		{
			"type": "patchouli:crafting",
			"recipe": "immersiveweapons:mortar",
			"recipe2": "immersiveweapons:mortar_shell"
		}
	],
	"advancement": "minecraft:story/mine_stone"
}