{
  "parent": "minecraft:recipes/root",
  "rewards": {
    "recipes": [
      "immersiveweapons:ventus_helmet"
    ]
  },
  "criteria": {
    "ventus_shard": {
      "trigger": "minecraft:inventory_changed",
      "conditions": {
        "items": [
          {
            "items": [
              "immersiveweapons:ventus_shard"
            ]
          }
        ]
      }
    },
    "has_the_recipe": {
      "trigger": "minecraft:recipe_unlocked",
      "conditions": {
        "recipe": "immersiveweapons:ventus_helmet"
      }
    }
  },
  "requirements": [
    [
      "ventus_shard",
      "has_the_recipe"
    ]
  ]
}